{
  "type": "Catalog",
  "id": "064_135602_IW",
  "stac_version": "1.0.0",
  "description": "Catalog of items from uw-subsidence with id 064_135602_IW",
  "links": [
    {
      "rel": "root",
      "href": "../../catalog.json",
      "type": "application/json"
    },
    {
      "rel": "child",
      "href": "./2019/catalog.json",
      "type": "application/json"
    },
    {
      "rel": "child",
      "href": "./2020/catalog.json",
      "type": "application/json"
    },
    {
      "rel": "child",
      "href": "./2021/catalog.json",
      "type": "application/json"
    },
    {
      "rel": "child",
      "href": "./2022/catalog.json",
      "type": "application/json"
    },
    {
      "rel": "child",
      "href": "./2023/catalog.json",
      "type": "application/json"
    },
    {
      "rel": "parent",
      "href": "../collection.json",
      "type": "application/json",
      "title": "ASF S1 BURST INTERFEROGRAMS"
    }
  ]
}